{
  "$schema": "https://json-schema.org/draft/2020-12/schema",
  "$id": "https://offlyn.ai/schemas/robotics_action.json",
  "title": "RoboticsAction",
  "description": "Structured robot action submitted by the autonomy layer for Verify Core policy evaluation before actuation.",
  "type": "object",
  "required": ["robot_id", "action", "source"],
  "additionalProperties": false,
  "properties": {
    "robot_id": {
      "type": "string",
      "minLength": 1,
      "description": "Unique identifier for the robot submitting the action."
    },
    "mission_id": {
      "type": "string",
      "minLength": 1,
      "description": "Optional mission or task identifier for audit correlation."
    },
    "action": {
      "type": "string",
      "enum": ["move", "stop", "turn", "emergency_stop"],
      "description": "Proposed actuation command type."
    },
    "linear_x": {
      "type": "number",
      "minimum": -2.0,
      "maximum": 2.0,
      "description": "Forward/backward velocity in m/s (required for move)."
    },
    "angular_z": {
      "type": "number",
      "minimum": -3.14,
      "maximum": 3.14,
      "description": "Yaw rate in rad/s (required for move and turn)."
    },
    "zone": {
      "type": "string",
      "enum": ["normal", "restricted", "human_zone"],
      "description": "Declared zone context for geofence policy checks."
    },
    "human_nearby": {
      "type": "boolean",
      "description": "Whether a human is detected within proximity threshold."
    },
    "source": {
      "type": "string",
      "minLength": 1,
      "description": "Origin of the proposed action (e.g. autonomy_planner)."
    }
  },
  "allOf": [
    {
      "if": { "properties": { "action": { "const": "move" } }, "required": ["action"] },
      "then": { "required": ["linear_x", "angular_z"] }
    },
    {
      "if": { "properties": { "action": { "const": "turn" } }, "required": ["action"] },
      "then": { "required": ["angular_z"] }
    }
  ]
}
